tests/__init__.py
wass2s/__init__.py
wass2s/untitled.py
wass2s/untitled1.py
wass2s/utils.py
wass2s/was_EnsBMA.py
wass2s/was_analog.py
wass2s/was_bias_correction.py
wass2s/was_cca.py
wass2s/was_compute_predictand.py
wass2s/was_cross_validate.py
wass2s/was_download.py
wass2s/was_eof.py
wass2s/was_hydro_processing.py
wass2s/was_linear_models.py
wass2s/was_machine_learning.py
wass2s/was_merge_predictand.py
wass2s/was_mme.py
wass2s/was_mme_bma_sloughter_with_quantiles.py
wass2s/was_mme_flexible_ngr_corrected.py
wass2s/was_mme_gp_corrected.py
wass2s/was_mme_ngr_corrected.py
wass2s/was_mme_roebber_ga_corrected.py
wass2s/was_pcr.py
wass2s/was_transformdata.py
wass2s/was_verification.py
wass2s-0.2.19.dist-info/METADATA
wass2s-0.2.19.dist-info/WHEEL
wass2s-0.2.19.dist-info/top_level.txt
wass2s-0.2.19.dist-info/RECORD
