Metadata-Version: 2.4
Name: wass2s
Version: 0.2.19
Summary: A Python package for seasonal climate forecast.
Home-page: https://github.com/hmandela/WASS2S
Author: HOUNGNIBO C. M. Mandela
Author-email: hmandelahmadiba@gmail.com
License: GPL-3.0
Classifier: Programming Language :: Python :: 3
Classifier: License :: OSI Approved :: GNU General Public License v3 (GPLv3)
Classifier: Operating System :: OS Independent
Requires-Python: >=3.12
Requires-Dist: statsmodels
Requires-Dist: pykrige
Requires-Dist: cartopy
Requires-Dist: scipy==1.11.3
Requires-Dist: matplotlib==3.7.3
Requires-Dist: xeofs==3.0.4
Requires-Dist: xskillscore==0.0.26
Requires-Dist: properscoring
Requires-Dist: cdsapi==0.7.4
Requires-Dist: rasterio
Requires-Dist: geopandas
Requires-Dist: shapely
Requires-Dist: rioxarray
Dynamic: author
Dynamic: author-email
Dynamic: classifier
Dynamic: description
Dynamic: description-content-type
Dynamic: home-page
Dynamic: license
Dynamic: requires-dist
Dynamic: requires-python
Dynamic: summary
